pysafie/__init__.py
pysafie-0.3.dist-info/METADATA
pysafie-0.3.dist-info/WHEEL
pysafie-0.3.dist-info/top_level.txt
pysafie-0.3.dist-info/RECORD
