Metadata-Version: 2.1
Name: pysafie
Version: 0.3
Summary: Safie API client library for Python
Home-page: https://github.com/kndt84/pysafie
Author: kndt84
Author-email: takashi.kaneda@gmail.com
License: UNKNOWN
Platform: UNKNOWN
Classifier: Programming Language :: Python :: 3
Classifier: License :: OSI Approved :: MIT License
Classifier: Operating System :: OS Independent
Requires-Python: >=3.7
Requires-Dist: requests
